uroko/__init__.py
uroko/cli.py
uroko-0.2.2.dist-info/entry_points.txt
uroko-0.2.2.dist-info/LICENSE
uroko-0.2.2.dist-info/WHEEL
uroko-0.2.2.dist-info/METADATA
uroko-0.2.2.dist-info/RECORD
